geekjob_python_helpers/__init__.py
geekjob_python_helpers/dictobject.py
geekjob_python_helpers/fs.py
geekjob_python_helpers/shortlambda.py
geekjob_python_helpers/singleton.py
geekjob_python_helpers-1.0.1.dist-info/LICENSE
geekjob_python_helpers-1.0.1.dist-info/METADATA
geekjob_python_helpers-1.0.1.dist-info/WHEEL
geekjob_python_helpers-1.0.1.dist-info/top_level.txt
geekjob_python_helpers-1.0.1.dist-info/RECORD
